{
  "2026-03-30": {
    "summary": {
      "totalFiles": 2,
      "totalLeads": 102,
      "totalShown": 85,
      "byAgent": {
        "YahiaH": {
          "files": 2,
          "leads": 102,
          "shown": 85
        }
      }
    },
    "records": [
      {
        "transactionId": "mncypptujp318zh8e",
        "agent": "YahiaH",
        "filename": "Some X Show - ADLM 2026 (Association for Diagnostics & Laboratory Medicine) - Annual Scientific Meeting & Clinical Lab Expo - July 28-30, 2026 - Anaheim Convention Center - Anaheim, CA, USA. YahiaH.xlsx",
        "mode": "SOME",
        "shown": 83,
        "hidden": 17,
        "total": 100,
        "time": "11:05:04"
      },
      {
        "transactionId": "mncypt9itchi2on00",
        "agent": "YahiaH",
        "filename": "X_Show_PRINTING_United_Expo_2026_The_North_American_Gateway_to_the.xlsx",
        "mode": "STANDARD",
        "shown": 2,
        "hidden": 0,
        "total": 2,
        "time": "11:05:09"
      }
    ]
  }
}